[
    {
        "title": "Fundamentals of Accounting ðŸ“š",
        "ques": "What are the **basic accounting concepts**?",
        "answer": {
            "type": "text",
            "lang": null,
            "content": "**Basic Concepts**:\n1. Business Entity Concept\n2. Going Concern Concept\n3. Money Measurement Concept\n4. Cost Concept\n5. Dual Aspect (Double Entry)\n6. Accounting Period Concept\n7. Matching Concept\n8. Accrual Concept"
        },
        "explanation": "These concepts form the ***foundation*** of financial accounting."
    },
    {
        "title": "Indian Accounting Standards ðŸ“‹",
        "ques": "What is the difference between **Ind AS** and **IGAAP**?",
        "answer": {
            "type": "text",
            "lang": null,
            "content": "**Ind AS**: Indian Accounting Standards converged with IFRS\n* Fair value focus\n* Mandatory for large companies\n* Principle-based approach\n\n**IGAAP**: Indian Generally Accepted Accounting Principles\n* Historical cost focus\n* For smaller companies\n* More rule-based"
        },
        "explanation": "Ind AS is ***converged with IFRS*** for global consistency."
    },
    {
        "title": "Journal Entries ðŸ“",
        "ques": "Explain the **rules of debit and credit**.",
        "answer": {
            "type": "text",
            "lang": null,
            "content": "**Golden Rules**:\n* Personal A/c: Debit the receiver, Credit the giver\n* Real A/c: Debit what comes in, Credit what goes out\n* Nominal A/c: Debit expenses/losses, Credit incomes/gains\n\n**Modern Approach**: Assets, Expenses = Debit increase; Liabilities, Income, Equity = Credit increase"
        },
        "explanation": "Both approaches give ***same result*** - choose one consistently."
    },
    {
        "title": "Bank Reconciliation ðŸ¦",
        "ques": "What items cause differences in **bank reconciliation**?",
        "answer": {
            "type": "text",
            "lang": null,
            "content": "**Timing Differences**:\n* Cheques issued but not presented\n* Cheques deposited but not cleared\n* Direct credits/debits not yet recorded\n\n**Errors**:\n* Recording errors in cash book\n* Bank errors\n* Omissions"
        },
        "explanation": "Reconciliation ensures ***accuracy*** of cash records."
    },
    {
        "title": "Depreciation Methods âš™ï¸",
        "ques": "Compare **straight-line** and **WDV** depreciation methods.",
        "answer": {
            "type": "text",
            "lang": null,
            "content": "**Straight-Line**: Equal amount each year\n* Formula: (Cost - Residual) / Life\n* Higher profit in early years\n\n**Written Down Value (WDV)**: Fixed rate on reducing balance\n* Formula: Rate x Book Value\n* Higher depreciation in early years\n* Preferred for tax purposes in India"
        },
        "explanation": "Choice affects reported ***profit and tax***."
    },
    {
        "title": "Final Accounts ðŸ“Š",
        "ques": "What are the components of **final accounts**?",
        "answer": {
            "type": "text",
            "lang": null,
            "content": "**Components**:\n1. Trading Account: Gross Profit/Loss\n2. Profit & Loss Account: Net Profit/Loss\n3. Balance Sheet: Financial Position\n\n**Adjustments**: Closing stock, prepaid, outstanding, provisions"
        },
        "explanation": "Final accounts summarize ***business performance*** and position."
    },
    {
        "title": "Bill of Exchange ðŸ“œ",
        "ques": "What is a **bill of exchange** and who are the parties?",
        "answer": {
            "type": "text",
            "lang": null,
            "content": "**Definition**: Written unconditional order to pay a sum on demand or at a fixed date\n\n**Parties**:\n* Drawer: Person who draws the bill\n* Drawee: Person on whom bill is drawn\n* Payee: Person to whom payment is made\n\n**Types**: Time bill, Demand bill"
        },
        "explanation": "Bills are ***negotiable instruments*** for credit transactions."
    },
    {
        "title": "Accounting for Consignment ðŸ“¦",
        "ques": "How is **consignment accounting** done?",
        "answer": {
            "type": "text",
            "lang": null,
            "content": "**Consignor**: Sends goods, remains owner until sale\n* Goods on Consignment Account\n* Commission to consignee\n\n**Consignee**: Sells goods for commission\n* Consignment Inward Account\n* Account Sales sent to consignor\n\n**Revenue recognition**: When consignee sells"
        },
        "explanation": "Ownership passes to buyer, ***not consignee***."
    },
    {
        "title": "Branch Accounts ðŸ¢",
        "ques": "What are the **methods for branch accounting**?",
        "answer": {
            "type": "text",
            "lang": null,
            "content": "**Methods**:\n1. Debtors System (for small branches)\n2. Stock and Debtors System\n3. Final Accounts System\n4. Wholesale Branch Method\n\n**Choice depends on**: Branch size, independence, control needs"
        },
        "explanation": "Larger branches often use ***final accounts system***."
    },
    {
        "title": "Partnership Accounting ðŸ¤",
        "ques": "What are the **adjustments in partnership accounts**?",
        "answer": {
            "type": "text",
            "lang": null,
            "content": "**Key Adjustments**:\n* Interest on capital\n* Interest on drawings\n* Salary to partners\n* Commission to partners\n* Profit sharing ratio\n\n**On changes**: Goodwill, revaluation, capital adjustments"
        },
        "explanation": "Partnership deed governs ***all adjustments***."
    },
    {
        "title": "Company Accounts Basics ðŸ›ï¸",
        "ques": "What are the types of **share capital**?",
        "answer": {
            "type": "text",
            "lang": null,
            "content": "**Types**:\n* Authorized/Nominal Capital\n* Issued Capital\n* Subscribed Capital\n* Called-up Capital\n* Paid-up Capital\n\n**Share Premium**: Excess over face value\n**Calls in Arrears**: Amounts not yet paid"
        },
        "explanation": "Companies Act 2013 governs ***company capital***."
    },
    {
        "title": "Issue of Debentures ðŸ“œ",
        "ques": "How is **issue of debentures** accounted for?",
        "answer": {
            "type": "text",
            "lang": null,
            "content": "**At Par**: Issue price = Face value\n**At Premium**: Issue price > Face value\n**At Discount**: Issue price < Face value\n\n**Redemption consideration**: Sinking fund, own debentures"
        },
        "explanation": "Discount on issue is ***written off*** over life."
    },
    {
        "title": "Hire Purchase Accounting ðŸš—",
        "ques": "How is **hire purchase** accounted for?",
        "answer": {
            "type": "text",
            "lang": null,
            "content": "**Purchaser**:\n* Asset recognized at cash price\n* Interest charged to P&L\n* Depreciation on asset\n\n**Vendor**:\n* Sale at cash price\n* Interest income recognized\n\n**Methods**: Total interest method, Interest allocated method"
        },
        "explanation": "Ownership passes after ***final payment***."
    },
    {
        "title": "Investment Accounting ðŸ’°",
        "ques": "How are **investments** accounted for?",
        "answer": {
            "type": "text",
            "lang": null,
            "content": "**Classification**:\n* Current (trading): Lower of cost or market\n* Non-current (long-term): Cost less impairment\n\n**Entries for**: Purchase, sale, dividend, bonus, rights"
        },
        "explanation": "Ex-dividend and cum-dividend affect ***cost allocation***."
    },
    {
        "title": "Amalgamation Accounting ðŸ”„",
        "ques": "What are the methods of **amalgamation accounting**?",
        "answer": {
            "type": "text",
            "lang": null,
            "content": "**Two Methods** (AS-14):\n1. **Pooling of Interests**: Business combination continuation\n2. **Purchase Method**: One company acquires another\n\n**Difference in**: Asset valuation, reserve treatment, goodwill"
        },
        "explanation": "Ind AS uses ***acquisition method*** primarily."
    }
]